sphinx_termynal/__init__.py
sphinx_termynal/termynal.py
sphinx_termynal/static/termynal.css
sphinx_termynal/static/termynal.js
sphinx_termynal-0.2.1.dist-info/licenses/LICENSE
sphinx_termynal-0.2.1.dist-info/METADATA
sphinx_termynal-0.2.1.dist-info/WHEEL
sphinx_termynal-0.2.1.dist-info/top_level.txt
sphinx_termynal-0.2.1.dist-info/RECORD
