Metadata-Version: 2.4
Name: sphinx-termynal
Version: 0.2.1
Summary: Animated terminal window for Sphinx
Author-email: Prajeesh Ag <prajeeshag@gmail.com>
License: MIT License
Project-URL: homepage, https://sphinx-termynal.prajeeshag.com
Project-URL: repository, https://github.com/prajeeshag/sphinx-termynal
Project-URL: documentation, https://sphinx-termynal.prajeeshag.com
License-File: LICENSE
Requires-Dist: sphinx
Dynamic: license-file
